{"mcpServers":{"filesystem-projects":{"command":"npx","args":["-y","@modelcontextprotocol/server-filesystem","C:/Users/pavel/projects"],"alwaysAllow":["read_text_file","list_directory","directory_tree","read_multiple_files","write_file","create_directory","read_file","edit_file"],"description":"Filesystem access to projects directory"},"filesystem-agentic":{"command":"npx","args":["-y","@modelcontextprotocol/server-filesystem","C:/Users/pavel/vscodeportable/agentic"],"description":"Filesystem access to agentic repository directory (read-only reference)","alwaysAllow":["read_multiple_files","create_directory","list_directory","read_text_file"]},"memory":{"command":"npx","args":["-y","@modelcontextprotocol/server-memory"],"description":"In-memory knowledge graph for entities, relations, and observations","alwaysAllow":["read_graph","search_nodes","open_nodes"]},"git":{"command":"npx","args":["-y","git-mcp"],"description":"Git repository operations","alwaysAllow":["git_status","git_log","git_branch","git_show"]},"github":{"command":"npx","args":["-y","@modelcontextprotocol/server-github"],"env":{"GITHUB_TOKEN":"${GITHUB_TOKEN}"},"description":"GitHub API for repo management, issues, and PRs","alwaysAllow":["get_file_contents","list_commits","list_issues","list_pull_requests","search_code"]},"time":{"command":"uvx","args":["mcp-server-time"],"description":"Time and date operations with timezone support","alwaysAllow":["get_current_time","convert_time"]},"fetch":{"command":"uvx","args":["mcp-server-fetch"],"description":"HTTP requests for fetching external content and APIs","alwaysAllow":["fetch"]}},"security":{"pathValidation":{"enabled":true,"allowedPaths":["C:/Users/pavel/projects","C:/Users/pavel/vscodeportable/agentic"],"blockedPaths":["C:/Windows","C:/Program Files","C:/Program Files (x86)","C:/Users/pavel/.ssh","C:/Users/pavel/.gnupg","C:/Users/pavel/AppData"]},"permissionControl":{"writeOperationsRequireApproval":true,"dangerousOperationsRequireApproval":true,"safeReadOperations":["read_text_file","list_directory","directory_tree","read_multiple_files","get_current_time","convert_time","read_graph","search_nodes","open_nodes","git_status","git_log","git_branch","git_show","get_file_contents","list_commits","list_issues","list_pull_requests","fetch"]}}}